pezzetti/__init__.py
pezzetti/errors.py
pezzetti/feature_engineering.py
pezzetti/metadata.py
pezzetti/utils.py
pezzetti/sources/__init__.py
pezzetti/sources/socrata.py
pezzetti-0.1.0.dist-info/METADATA
pezzetti-0.1.0.dist-info/WHEEL
pezzetti-0.1.0.dist-info/top_level.txt
pezzetti-0.1.0.dist-info/RECORD
