Metadata-Version: 2.1
Name: pezzetti
Version: 0.1.0
Summary: A package of little pieces.
Author: Matt Triano
License: UNKNOWN
Platform: UNKNOWN
